tcarlae-0.2.0.dist-info/METADATA
tcarlae-0.2.0.dist-info/WHEEL
tcarlae-0.2.0.dist-info/entry_points.txt
tcarlae/__init__.py
tcarlae/cli.py
tcarlae-0.2.0.dist-info/RECORD
