Metadata-Version: 2.1
Name: tcarlae
Version: 0.2.0
Summary: Minimal Python repository with a simple development workflow. Share and enjoy!
Author-Email: David Seaward <david@librem.one>
License: CC0-1.0
Requires-Python: >=3.10
